README.md
setup.py
python_apollo_client/__init__.py
python_apollo_client/python_apollo_client.py
python_apollo_client.egg-info/PKG-INFO
python_apollo_client.egg-info/SOURCES.txt
python_apollo_client.egg-info/dependency_links.txt
python_apollo_client.egg-info/not-zip-safe
python_apollo_client.egg-info/requires.txt
python_apollo_client.egg-info/top_level.txt