Metadata-Version: 2.1
Name: python-apollo-client
Version: 0.0.2
Summary: a python client for apollo
Home-page: UNKNOWN
Author: 
Author-email: 526861348@qq.com
License: UNKNOWN
Platform: any
Classifier: Programming Language :: Python :: 3.5
Classifier: Programming Language :: Python :: 2.7
